{
  "metadata": {
    "soundFile": "C:\\Users\\265600\\Desktop\\Trial2\\3d\\public\\audio\\intro.wav",
    "duration": 9.37
  },
  "mouthCues": [
    { "start": 0.00, "end": 0.10, "value": "X" },
    { "start": 0.10, "end": 0.22, "value": "C" },
    { "start": 0.22, "end": 0.29, "value": "B" },
    { "start": 0.29, "end": 0.37, "value": "A" },
    { "start": 0.37, "end": 0.55, "value": "C" },
    { "start": 0.55, "end": 0.63, "value": "A" },
    { "start": 0.63, "end": 0.85, "value": "B" },
    { "start": 0.85, "end": 0.92, "value": "C" },
    { "start": 0.92, "end": 0.99, "value": "B" },
    { "start": 0.99, "end": 1.06, "value": "G" },
    { "start": 1.06, "end": 1.25, "value": "D" },
    { "start": 1.25, "end": 1.30, "value": "C" },
    { "start": 1.30, "end": 1.55, "value": "B" },
    { "start": 1.55, "end": 1.62, "value": "C" },
    { "start": 1.62, "end": 1.68, "value": "B" },
    { "start": 1.68, "end": 1.75, "value": "C" },
    { "start": 1.75, "end": 1.84, "value": "A" },
    { "start": 1.84, "end": 1.90, "value": "C" },
    { "start": 1.90, "end": 1.95, "value": "E" },
    { "start": 1.95, "end": 2.02, "value": "F" },
    { "start": 2.02, "end": 2.16, "value": "G" },
    { "start": 2.16, "end": 2.23, "value": "F" },
    { "start": 2.23, "end": 2.37, "value": "B" },
    { "start": 2.37, "end": 2.45, "value": "E" },
    { "start": 2.45, "end": 2.49, "value": "B" },
    { "start": 2.49, "end": 2.67, "value": "C" },
    { "start": 2.67, "end": 2.74, "value": "B" },
    { "start": 2.74, "end": 2.81, "value": "H" },
    { "start": 2.81, "end": 2.88, "value": "B" },
    { "start": 2.88, "end": 2.95, "value": "C" },
    { "start": 2.95, "end": 3.16, "value": "D" },
    { "start": 3.16, "end": 3.30, "value": "B" },
    { "start": 3.30, "end": 3.58, "value": "E" },
    { "start": 3.58, "end": 3.72, "value": "G" },
    { "start": 3.72, "end": 3.86, "value": "C" },
    { "start": 3.86, "end": 4.33, "value": "B" },
    { "start": 4.33, "end": 4.52, "value": "D" },
    { "start": 4.52, "end": 4.59, "value": "B" },
    { "start": 4.59, "end": 4.66, "value": "C" },
    { "start": 4.66, "end": 4.74, "value": "A" },
    { "start": 4.74, "end": 4.82, "value": "C" },
    { "start": 4.82, "end": 4.96, "value": "G" },
    { "start": 4.96, "end": 5.10, "value": "C" },
    { "start": 5.10, "end": 5.24, "value": "B" },
    { "start": 5.24, "end": 5.38, "value": "G" },
    { "start": 5.38, "end": 5.45, "value": "C" },
    { "start": 5.45, "end": 5.52, "value": "B" },
    { "start": 5.52, "end": 5.60, "value": "A" },
    { "start": 5.60, "end": 5.86, "value": "C" },
    { "start": 5.86, "end": 6.42, "value": "B" },
    { "start": 6.42, "end": 6.50, "value": "A" },
    { "start": 6.50, "end": 6.59, "value": "C" },
    { "start": 6.59, "end": 6.80, "value": "B" },
    { "start": 6.80, "end": 7.01, "value": "C" },
    { "start": 7.01, "end": 7.36, "value": "B" },
    { "start": 7.36, "end": 7.64, "value": "C" },
    { "start": 7.64, "end": 7.92, "value": "B" },
    { "start": 7.92, "end": 8.35, "value": "X" },
    { "start": 8.35, "end": 8.39, "value": "F" },
    { "start": 8.39, "end": 8.43, "value": "B" },
    { "start": 8.43, "end": 8.51, "value": "A" },
    { "start": 8.51, "end": 8.61, "value": "C" },
    { "start": 8.61, "end": 8.75, "value": "B" },
    { "start": 8.75, "end": 9.03, "value": "F" },
    { "start": 9.03, "end": 9.37, "value": "X" }
  ]
}
